{
	"name": "DS2",
	"properties": {
		"linkedServiceName": {
			"referenceName": "LS_AzureBlobStorage001",
			"type": "LinkedServiceReference"
		},
		"annotations": [],
		"type": "DelimitedText",
		"typeProperties": {
			"location": {
				"type": "AzureBlobStorageLocation",
				"fileName": "orders.csv",
				"folderPath": "shop",
				"container": "container001"
			},
			"columnDelimiter": ",",
			"escapeChar": "\\",
			"firstRowAsHeader": true,
			"quoteChar": "\""
		},
		"schema": [
			{
				"name": "OrderID",
				"type": "String"
			},
			{
				"name": "CustomerID",
				"type": "String"
			},
			{
				"name": "OrderDate",
				"type": "String"
			},
			{
				"name": "ShipperID",
				"type": "String"
			},
			{
				"name": "address",
				"type": "String"
			}
		]
	},
	"type": "Microsoft.DataFactory/factories/datasets"
}